nredarwin/__init__.py
nredarwin/cli.py
nredarwin/webservice.py
nre_darwin_py-0.4.1.dist-info/LICENSE.txt
nre_darwin_py-0.4.1.dist-info/METADATA
nre_darwin_py-0.4.1.dist-info/WHEEL
nre_darwin_py-0.4.1.dist-info/entry_points.txt
nre_darwin_py-0.4.1.dist-info/top_level.txt
nre_darwin_py-0.4.1.dist-info/RECORD
