Metadata-Version: 2.1
Name: nre-darwin-py
Version: 0.4.1
Summary: A simple python wrapper around National Rail Enquires         LDBS SOAP Webservice
Home-page: https://github.com/robert-b-clarke/nre-darwin-py
Author: Robert Clarke
Author-email: rob@redanorak.co.uk
License: BSD License
Classifier: Framework :: Django
Classifier: Intended Audience :: Developers
Classifier: License :: OSI Approved :: BSD License
Classifier: Operating System :: OS Independent
Classifier: Programming Language :: Python
Classifier: Topic :: Internet :: WWW/HTTP
Classifier: Topic :: Internet :: WWW/HTTP :: Dynamic Content
Classifier: Development Status :: 4 - Beta
License-File: LICENSE.txt
Requires-Dist: suds-py3>=1.4.5.0
Requires-Dist: tabulate>=0.8.6
